mediqbox/pubmed/__init__.py
mediqbox/pubmed/pubmed.py
mediqbox_pubmed-0.0.4.dist-info/LICENSE
mediqbox_pubmed-0.0.4.dist-info/METADATA
mediqbox_pubmed-0.0.4.dist-info/WHEEL
mediqbox_pubmed-0.0.4.dist-info/top_level.txt
mediqbox_pubmed-0.0.4.dist-info/RECORD
