Metadata-Version: 2.1
Name: mediqbox-pubmed
Version: 0.0.4
Summary: A mediqbox component for PubMed query
License-File: LICENSE
Requires-Dist: mediqbox-abc ==0.0.4
Requires-Dist: biopython
Requires-Dist: pydantic
